apysigner.py
apysigner-4.0.0.dist-info/LICENSE
apysigner-4.0.0.dist-info/METADATA
apysigner-4.0.0.dist-info/WHEEL
apysigner-4.0.0.dist-info/top_level.txt
apysigner-4.0.0.dist-info/RECORD
